Metadata-Version: 2.1
Name: uagents-twilio
Version: 1.0.7
Summary: Use uagents to automate SMS/Whatsapp by twilio
Home-page: https://github.com/harshpatel199259/uagents_twilio
Author: Harsh
Author-email: harsh.patel@fetch.ai
Requires-Python: >=3.8.1,<3.12
Classifier: Intended Audience :: Developers
Classifier: License :: OSI Approved :: MIT License
Classifier: Operating System :: OS Independent
Classifier: Programming Language :: Python
Classifier: Programming Language :: Python :: 3
Classifier: Programming Language :: Python :: 3.9
Classifier: Programming Language :: Python :: 3.10
Classifier: Programming Language :: Python :: 3.11
Classifier: Programming Language :: Python :: 3 :: Only
Classifier: Topic :: Software Development :: Libraries :: Python Modules
Requires-Dist: fastapi (>=0.100.0,<0.101.0)
Requires-Dist: flake8 (==6.0.0)
Requires-Dist: pre-commit (==3.3.3)
Requires-Dist: python-decouple (==3.8)
Requires-Dist: uagents (==0.5.0)
Project-URL: Repository, https://github.com/harshpatel199259/uagents_twilio
